parallel_corpus/__init__.py
parallel_corpus/graph.py
parallel_corpus/py.typed
parallel_corpus/source_target.py
parallel_corpus/text_token.py
parallel_corpus/shared/__init__.py
parallel_corpus/shared/dicts.py
parallel_corpus/shared/diffs.py
parallel_corpus/shared/functional.py
parallel_corpus/shared/ids.py
parallel_corpus/shared/lists.py
parallel_corpus/shared/ranges.py
parallel_corpus/shared/str_map.py
parallel_corpus/shared/union_find.py
parallel_corpus/shared/unique_check.py
parallel_corpus-0.2.0.dist-info/METADATA
parallel_corpus-0.2.0.dist-info/WHEEL
parallel_corpus-0.2.0.dist-info/licenses/LICENSE
parallel_corpus-0.2.0.dist-info/RECORD
