Metadata-Version: 2.3
Name: parallel-corpus
Version: 0.2.0
Summary: Parallel corpus as a graph.
Author-email: Språkbanken Text <sb-info@svenska.gu.se>, Kristoffer Andersson <kristoffer.andersson@gu.se>
License: MIT
Classifier: Development Status :: 3 - Alpha
Classifier: Intended Audience :: Developers
Classifier: License :: OSI Approved :: MIT License
Classifier: Operating System :: MacOS :: MacOS X
Classifier: Operating System :: Microsoft :: Windows
Classifier: Operating System :: POSIX
Classifier: Operating System :: Unix
Classifier: Programming Language :: Python :: 3.9
Classifier: Programming Language :: Python :: 3.10
Classifier: Programming Language :: Python :: 3.11
Classifier: Programming Language :: Python :: 3.12
Classifier: Programming Language :: Python :: 3.13
Classifier: Programming Language :: Python :: Implementation :: CPython
Classifier: Topic :: Utilities
Requires-Python: >=3.9
Requires-Dist: diff-match-patch>=20230430
Requires-Dist: more-itertools>=10.2.0
Requires-Dist: strenum>=0.4.15
Requires-Dist: typing-extensions>=4.11.0
